.coveragerc
.gitignore
.travis.yml
AUTHORS.rst
CHANGELOG.rst
LICENSE.txt
README.rst
doc_requirements.txt
readthedocs.yml
requirements.txt
setup.cfg
setup.py
test-requirements.txt
docs/Makefile
docs/authors.rst
docs/changelog.rst
docs/changes.rst
docs/conf.py
docs/index.rst
docs/license.rst
docs/_static/.gitignore
src/sigma0/__init__.py
src/sigma0/oh_model.py
src/sigma0/skeleton.py
src/sigma0.egg-info/PKG-INFO
src/sigma0.egg-info/SOURCES.txt
src/sigma0.egg-info/dependency_links.txt
src/sigma0.egg-info/not-zip-safe
src/sigma0.egg-info/requires.txt
src/sigma0.egg-info/top_level.txt
tests/conftest.py
tests/test_skeleton.py