Metadata-Version: 2.1
Name: sigma0
Version: 0.0.1
Summary: Backscatter models
Home-page: https://www.geo.tuwien.ac.at/
Author: TU Wien
Author-email: remote.sensing@geo.tuwien.ac.at
License: mit
Project-URL: Documentation, http://sigma0.readthedocs.org/
Platform: any
Classifier: Development Status :: 4 - Beta
Classifier: Programming Language :: Python
Requires-Python: >=3.6
Provides-Extra: testing
